pyjwt3/__init__.py
pyjwt3/_jwt.py
pyjwt3-1.0.0.dist-info/METADATA
pyjwt3-1.0.0.dist-info/WHEEL
pyjwt3-1.0.0.dist-info/top_level.txt
pyjwt3-1.0.0.dist-info/RECORD
