Metadata-Version: 2.1
Name: pyjwt3
Version: 1.0.0
Summary: 用于生成和验证JWT令牌的Python模块
Home-page: https://gitee.com/yangyingyun/pyjwt
Author: ZhongYang
Author-email: 19865697458@163.com
Classifier: Programming Language :: Python :: 3
Classifier: Operating System :: OS Independent
